{
 "cards": [
  {
   "card": "Waste Generator"
  },
  {
   "card": "Avg. Cost PT"
  },
  {
   "card": "Waste Qty"
  },
  {
   "card": "Approved"
  },
  {
   "card": "Not Classified"
  }
 ],
 "charts": [
  {
   "chart": "No. of Suppliers in Each State",
   "width": "Full"
  },
  {
   "chart": "Quantity in Each City",
   "width": "Full"
  },
  {
   "chart": "Round Trip Cost in Each City",
   "width": "Full"
  },
  {
   "chart": "Top 5 Suppliers",
   "width": "Full"
  }
 ],
 "creation": "2024-06-06 14:36:31.090960",
 "dashboard_name": "Waste Food Suppliers",
 "docstatus": 0,
 "doctype": "Dashboard",
 "idx": 0,
 "is_default": 1,
 "is_standard": 1,
 "modified": "2024-06-06 14:56:56.870726",
 "modified_by": "Administrator",
 "module": "Masar Waste Food",
 "name": "Waste Food Suppliers",
 "owner": "Administrator"
}